{
    "historic": {
        "lat": 47.9961,
        "lon": 7.8531,
        "timezone": "Europe/Berlin",
        "timezone_offset": 3600,
        "current": {
            "dt": 1673611477,
            "sunrise": 1673594096,
            "sunset": 1673625531,
            "temp": 283.54,
            "feels_like": 282.59,
            "pressure": 1016,
            "humidity": 75,
            "dew_point": 279.31,
            "uvi": 0.56,
            "clouds": 26,
            "visibility": 10000,
            "wind_speed": 4.92,
            "wind_deg": 291,
            "wind_gust": 11.18,
            "weather": [
                {
                    "id": 802,
                    "main": "Clouds",
                    "description": "scattered clouds",
                    "icon": "03d"
                }
            ]
        },
        "hourly": [
            {
                "dt": 1673568000,
                "temp": 284.26,
                "feels_like": 283.2,
                "pressure": 1015,
                "humidity": 68,
                "dew_point": 278.58,
                "uvi": 0,
                "clouds": 100,
                "visibility": 10000,
                "wind_speed": 4.47,
                "wind_deg": 203,
                "wind_gust": 11.62,
                "weather": [
                    {
                        "id": 804,
                        "main": "Clouds",
                        "description": "overcast clouds",
                        "icon": "04n"
                    }
                ]
            },
            {
                "dt": 1673571600,
                "temp": 284.36,
                "feels_like": 283.31,
                "pressure": 1014,
                "humidity": 68,
                "dew_point": 278.68,
                "uvi": 0,
                "clouds": 100,
                "visibility": 10000,
                "wind_speed": 4.02,
                "wind_deg": 184,
                "wind_gust": 7.6,
                "weather": [
                    {
                        "id": 804,
                        "main": "Clouds",
                        "description": "overcast clouds",
                        "icon": "04n"
                    }
                ]
            },
            {
                "dt": 1673575200,
                "temp": 283.97,
                "feels_like": 282.96,
                "pressure": 1014,
                "humidity": 71,
                "dew_point": 278.93,
                "uvi": 0,
                "clouds": 100,
                "visibility": 10000,
                "wind_speed": 3.58,
                "wind_deg": 289,
                "wind_gust": 8.94,
                "weather": [
                    {
                        "id": 804,
                        "main": "Clouds",
                        "description": "overcast clouds",
                        "icon": "04n"
                    }
                ]
            },
            {
                "dt": 1673578800,
                "temp": 283.71,
                "feels_like": 282.73,
                "pressure": 1014,
                "humidity": 73,
                "dew_point": 279.08,
                "uvi": 0,
                "clouds": 100,
                "visibility": 10000,
                "wind_speed": 4.47,
                "wind_deg": 239,
                "wind_gust": 10.73,
                "weather": [
                    {
                        "id": 804,
                        "main": "Clouds",
                        "description": "overcast clouds",
                        "icon": "04n"
                    }
                ]
            },
            {
                "dt": 1673582400,
                "temp": 283.56,
                "feels_like": 282.61,
                "pressure": 1013,
                "humidity": 75,
                "dew_point": 279.33,
                "uvi": 0,
                "clouds": 100,
                "visibility": 10000,
                "wind_speed": 6.71,
                "wind_deg": 182,
                "wind_gust": 11.18,
                "weather": [
                    {
                        "id": 804,
                        "main": "Clouds",
                        "description": "overcast clouds",
                        "icon": "04n"
                    }
                ]
            },
            {
                "dt": 1673586000,
                "temp": 283.12,
                "feels_like": 280.73,
                "pressure": 1014,
                "humidity": 78,
                "dew_point": 279.47,
                "uvi": 0,
                "clouds": 100,
                "visibility": 10000,
                "wind_speed": 4.92,
                "wind_deg": 215,
                "wind_gust": 11.62,
                "weather": [
                    {
                        "id": 804,
                        "main": "Clouds",
                        "description": "overcast clouds",
                        "icon": "04n"
                    }
                ]
            },
            {
                "dt": 1673589600,
                "temp": 283.08,
                "feels_like": 280.52,
                "pressure": 1013,
                "humidity": 80,
                "dew_point": 279.8,
                "uvi": 0,
                "clouds": 100,
                "visibility": 10000,
                "wind_speed": 5.36,
                "wind_deg": 203,
                "wind_gust": 10.73,
                "weather": [
                    {
                        "id": 804,
                        "main": "Clouds",
                        "description": "overcast clouds",
                        "icon": "04n"
                    }
                ]
            },
            {
                "dt": 1673593200,
                "temp": 283.15,
                "feels_like": 280.77,
                "pressure": 1013,
                "humidity": 81,
                "dew_point": 280.04,
                "uvi": 0,
                "clouds": 100,
                "visibility": 10000,
                "wind_speed": 4.92,
                "wind_deg": 203,
                "wind_gust": 11.18,
                "weather": [
                    {
                        "id": 804,
                        "main": "Clouds",
                        "description": "overcast clouds",
                        "icon": "04n"
                    }
                ]
            },
            {
                "dt": 1673596800,
                "temp": 283,
                "feels_like": 280.76,
                "pressure": 1014,
                "humidity": 84,
                "dew_point": 280.43,
                "uvi": 0.03,
                "clouds": 100,
                "visibility": 8980,
                "wind_speed": 4.47,
                "wind_deg": 209,
                "wind_gust": 10.73,
                "weather": [
                    {
                        "id": 502,
                        "main": "Rain",
                        "description": "heavy intensity rain",
                        "icon": "10d"
                    }
                ],
                "rain": {
                    "1h": 7.49
                }
            },
            {
                "dt": 1673600400,
                "temp": 282.63,
                "feels_like": 279.8,
                "pressure": 1014,
                "humidity": 86,
                "dew_point": 280.41,
                "uvi": 0.09,
                "clouds": 100,
                "visibility": 4486,
                "wind_speed": 5.81,
                "wind_deg": 126,
                "wind_gust": 9.83,
                "weather": [
                    {
                        "id": 804,
                        "main": "Clouds",
                        "description": "overcast clouds",
                        "icon": "04d"
                    }
                ]
            },
            {
                "dt": 1673604000,
                "temp": 283.09,
                "feels_like": 280.69,
                "pressure": 1015,
                "humidity": 81,
                "dew_point": 279.99,
                "uvi": 0.44,
                "clouds": 100,
                "visibility": 10000,
                "wind_speed": 4.92,
                "wind_deg": 203,
                "wind_gust": 12.07,
                "weather": [
                    {
                        "id": 804,
                        "main": "Clouds",
                        "description": "overcast clouds",
                        "icon": "04d"
                    }
                ]
            },
            {
                "dt": 1673607600,
                "temp": 283.95,
                "feels_like": 283.07,
                "pressure": 1015,
                "humidity": 76,
                "dew_point": 279.89,
                "uvi": 0.56,
                "clouds": 91,
                "visibility": 10000,
                "wind_speed": 4.02,
                "wind_deg": 226,
                "wind_gust": 9.39,
                "weather": [
                    {
                        "id": 804,
                        "main": "Clouds",
                        "description": "overcast clouds",
                        "icon": "04d"
                    }
                ]
            },
            {
                "dt": 1673611200,
                "temp": 283.54,
                "feels_like": 282.59,
                "pressure": 1016,
                "humidity": 75,
                "dew_point": 279.31,
                "uvi": 0.56,
                "clouds": 26,
                "visibility": 10000,
                "wind_speed": 4.92,
                "wind_deg": 291,
                "wind_gust": 11.18,
                "weather": [
                    {
                        "id": 802,
                        "main": "Clouds",
                        "description": "scattered clouds",
                        "icon": "03d"
                    }
                ]
            },
            {
                "dt": 1673614800,
                "temp": 283.49,
                "feels_like": 282.46,
                "pressure": 1016,
                "humidity": 72,
                "dew_point": 278.67,
                "uvi": 0.61,
                "clouds": 39,
                "visibility": 10000,
                "wind_speed": 4.02,
                "wind_deg": 203,
                "wind_gust": 9.83,
                "weather": [
                    {
                        "id": 500,
                        "main": "Rain",
                        "description": "light rain",
                        "icon": "10d"
                    }
                ],
                "rain": {
                    "1h": 0.75
                }
            },
            {
                "dt": 1673618400,
                "temp": 281.34,
                "feels_like": 280.03,
                "pressure": 1016,
                "humidity": 82,
                "dew_point": 278.45,
                "uvi": 0.34,
                "clouds": 55,
                "visibility": 10000,
                "wind_speed": 2.24,
                "wind_deg": 217,
                "wind_gust": 4.47,
                "weather": [
                    {
                        "id": 803,
                        "main": "Clouds",
                        "description": "broken clouds",
                        "icon": "04d"
                    }
                ]
            },
            {
                "dt": 1673622000,
                "temp": 281.32,
                "feels_like": 279.12,
                "pressure": 1017,
                "humidity": 79,
                "dew_point": 277.9,
                "uvi": 0.12,
                "clouds": 70,
                "visibility": 5400,
                "wind_speed": 3.58,
                "wind_deg": 155,
                "wind_gust": 6.26,
                "weather": [
                    {
                        "id": 803,
                        "main": "Clouds",
                        "description": "broken clouds",
                        "icon": "04d"
                    }
                ]
            },
            {
                "dt": 1673625600,
                "temp": 280.9,
                "feels_like": 279.18,
                "pressure": 1018,
                "humidity": 81,
                "dew_point": 277.85,
                "uvi": 0,
                "clouds": 77,
                "visibility": 8859,
                "wind_speed": 2.68,
                "wind_deg": 192,
                "wind_gust": 8.05,
                "weather": [
                    {
                        "id": 803,
                        "main": "Clouds",
                        "description": "broken clouds",
                        "icon": "04n"
                    }
                ]
            },
            {
                "dt": 1673629200,
                "temp": 281.31,
                "feels_like": 278.47,
                "pressure": 1018,
                "humidity": 80,
                "dew_point": 278.07,
                "uvi": 0,
                "clouds": 82,
                "visibility": 8516,
                "wind_speed": 4.92,
                "wind_deg": 198,
                "wind_gust": 9.39,
                "weather": [
                    {
                        "id": 500,
                        "main": "Rain",
                        "description": "light rain",
                        "icon": "10n"
                    }
                ],
                "rain": {
                    "1h": 0.27
                }
            },
            {
                "dt": 1673632800,
                "temp": 280.32,
                "feels_like": 277.44,
                "pressure": 1020,
                "humidity": 86,
                "dew_point": 278.14,
                "uvi": 0,
                "clouds": 8,
                "visibility": 10000,
                "wind_speed": 4.47,
                "wind_deg": 203,
                "wind_gust": 9.39,
                "weather": [
                    {
                        "id": 501,
                        "main": "Rain",
                        "description": "moderate rain",
                        "icon": "10n"
                    }
                ],
                "rain": {
                    "1h": 1.15
                }
            },
            {
                "dt": 1673636400,
                "temp": 279.99,
                "feels_like": 277.5,
                "pressure": 1020,
                "humidity": 85,
                "dew_point": 277.65,
                "uvi": 0,
                "clouds": 17,
                "visibility": 10000,
                "wind_speed": 3.58,
                "wind_deg": 187,
                "wind_gust": 7.15,
                "weather": [
                    {
                        "id": 801,
                        "main": "Clouds",
                        "description": "few clouds",
                        "icon": "02n"
                    }
                ]
            },
            {
                "dt": 1673640000,
                "temp": 280.3,
                "feels_like": 278.46,
                "pressure": 1021,
                "humidity": 80,
                "dew_point": 277.09,
                "uvi": 0,
                "clouds": 21,
                "visibility": 10000,
                "wind_speed": 2.68,
                "wind_deg": 234,
                "wind_gust": 6.71,
                "weather": [
                    {
                        "id": 801,
                        "main": "Clouds",
                        "description": "few clouds",
                        "icon": "02n"
                    }
                ]
            },
            {
                "dt": 1673643600,
                "temp": 280.2,
                "feels_like": 278.03,
                "pressure": 1022,
                "humidity": 83,
                "dew_point": 277.51,
                "uvi": 0,
                "clouds": 24,
                "visibility": 10000,
                "wind_speed": 3.13,
                "wind_deg": 209,
                "wind_gust": 7.15,
                "weather": [
                    {
                        "id": 801,
                        "main": "Clouds",
                        "description": "few clouds",
                        "icon": "02n"
                    }
                ]
            },
            {
                "dt": 1673647200,
                "temp": 279.86,
                "feels_like": 277.62,
                "pressure": 1022,
                "humidity": 86,
                "dew_point": 277.69,
                "uvi": 0,
                "clouds": 29,
                "visibility": 10000,
                "wind_speed": 3.13,
                "wind_deg": 224,
                "wind_gust": 5.81,
                "weather": [
                    {
                        "id": 802,
                        "main": "Clouds",
                        "description": "scattered clouds",
                        "icon": "03n"
                    }
                ]
            },
            {
                "dt": 1673650800,
                "temp": 280.1,
                "feels_like": 278.22,
                "pressure": 1022,
                "humidity": 86,
                "dew_point": 277.92,
                "uvi": 0,
                "clouds": 34,
                "visibility": 10000,
                "wind_speed": 2.68,
                "wind_deg": 203,
                "wind_gust": 4.92,
                "weather": [
                    {
                        "id": 500,
                        "main": "Rain",
                        "description": "light rain",
                        "icon": "10n"
                    }
                ],
                "rain": {
                    "1h": 0.49
                }
            }
        ]
    },
    "forecast": {
        "lat": 47.9961,
        "lon": 7.8531,
        "timezone": "Europe/Berlin",
        "timezone_offset": 3600,
        "hourly": [
            {
                "dt": 1673697600,
                "temp": 283.34,
                "feels_like": 282.19,
                "pressure": 1014,
                "humidity": 68,
                "dew_point": 277.71,
                "uvi": 0.56,
                "clouds": 100,
                "visibility": 10000,
                "wind_speed": 4.1,
                "wind_deg": 206,
                "wind_gust": 12.22,
                "weather": [
                    {
                        "id": 804,
                        "main": "Clouds",
                        "description": "overcast clouds",
                        "icon": "04d"
                    }
                ],
                "pop": 0
            },
            {
                "dt": 1673701200,
                "temp": 283.31,
                "feels_like": 282.1,
                "pressure": 1014,
                "humidity": 66,
                "dew_point": 277.25,
                "uvi": 0.35,
                "clouds": 100,
                "visibility": 10000,
                "wind_speed": 4.73,
                "wind_deg": 205,
                "wind_gust": 13.34,
                "weather": [
                    {
                        "id": 804,
                        "main": "Clouds",
                        "description": "overcast clouds",
                        "icon": "04d"
                    }
                ],
                "pop": 0
            },
            {
                "dt": 1673704800,
                "temp": 283.22,
                "feels_like": 282.01,
                "pressure": 1014,
                "humidity": 66,
                "dew_point": 277.17,
                "uvi": 0.2,
                "clouds": 100,
                "visibility": 10000,
                "wind_speed": 6.22,
                "wind_deg": 218,
                "wind_gust": 14.45,
                "weather": [
                    {
                        "id": 804,
                        "main": "Clouds",
                        "description": "overcast clouds",
                        "icon": "04d"
                    }
                ],
                "pop": 0.09
            },
            {
                "dt": 1673708400,
                "temp": 282.42,
                "feels_like": 279.69,
                "pressure": 1015,
                "humidity": 75,
                "dew_point": 278.22,
                "uvi": 0.07,
                "clouds": 100,
                "visibility": 10000,
                "wind_speed": 5.37,
                "wind_deg": 203,
                "wind_gust": 14.69,
                "weather": [
                    {
                        "id": 500,
                        "main": "Rain",
                        "description": "light rain",
                        "icon": "10d"
                    }
                ],
                "pop": 0.57,
                "rain": {
                    "1h": 0.32
                }
            },
            {
                "dt": 1673712000,
                "temp": 282.36,
                "feels_like": 279.22,
                "pressure": 1014,
                "humidity": 75,
                "dew_point": 278.17,
                "uvi": 0,
                "clouds": 100,
                "visibility": 10000,
                "wind_speed": 6.53,
                "wind_deg": 213,
                "wind_gust": 16.1,
                "weather": [
                    {
                        "id": 500,
                        "main": "Rain",
                        "description": "light rain",
                        "icon": "10d"
                    }
                ],
                "pop": 0.82,
                "rain": {
                    "1h": 0.14
                }
            },
            {
                "dt": 1673715600,
                "temp": 281.94,
                "feels_like": 278.69,
                "pressure": 1013,
                "humidity": 86,
                "dew_point": 278.94,
                "uvi": 0,
                "clouds": 100,
                "visibility": 10000,
                "wind_speed": 6.51,
                "wind_deg": 209,
                "wind_gust": 16.65,
                "weather": [
                    {
                        "id": 500,
                        "main": "Rain",
                        "description": "light rain",
                        "icon": "10n"
                    }
                ],
                "pop": 0.94,
                "rain": {
                    "1h": 0.56
                }
            },
            {
                "dt": 1673719200,
                "temp": 282.54,
                "feels_like": 279.23,
                "pressure": 1013,
                "humidity": 87,
                "dew_point": 279.63,
                "uvi": 0,
                "clouds": 100,
                "visibility": 10000,
                "wind_speed": 7.26,
                "wind_deg": 214,
                "wind_gust": 17.06,
                "weather": [
                    {
                        "id": 500,
                        "main": "Rain",
                        "description": "light rain",
                        "icon": "10n"
                    }
                ],
                "pop": 0.98,
                "rain": {
                    "1h": 0.69
                }
            },
            {
                "dt": 1673722800,
                "temp": 283.27,
                "feels_like": 282.5,
                "pressure": 1012,
                "humidity": 83,
                "dew_point": 279.58,
                "uvi": 0,
                "clouds": 100,
                "visibility": 10000,
                "wind_speed": 7.44,
                "wind_deg": 206,
                "wind_gust": 17.01,
                "weather": [
                    {
                        "id": 500,
                        "main": "Rain",
                        "description": "light rain",
                        "icon": "10n"
                    }
                ],
                "pop": 1,
                "rain": {
                    "1h": 0.65
                }
            },
            {
                "dt": 1673726400,
                "temp": 283.73,
                "feels_like": 282.91,
                "pressure": 1012,
                "humidity": 79,
                "dew_point": 279.4,
                "uvi": 0,
                "clouds": 100,
                "visibility": 10000,
                "wind_speed": 7.87,
                "wind_deg": 210,
                "wind_gust": 18.18,
                "weather": [
                    {
                        "id": 804,
                        "main": "Clouds",
                        "description": "overcast clouds",
                        "icon": "04n"
                    }
                ],
                "pop": 0.8
            },
            {
                "dt": 1673730000,
                "temp": 283.64,
                "feels_like": 282.83,
                "pressure": 1011,
                "humidity": 80,
                "dew_point": 279.4,
                "uvi": 0,
                "clouds": 100,
                "visibility": 10000,
                "wind_speed": 8.64,
                "wind_deg": 212,
                "wind_gust": 18.39,
                "weather": [
                    {
                        "id": 500,
                        "main": "Rain",
                        "description": "light rain",
                        "icon": "10n"
                    }
                ],
                "pop": 1,
                "rain": {
                    "1h": 0.15
                }
            },
            {
                "dt": 1673733600,
                "temp": 283.75,
                "feels_like": 282.88,
                "pressure": 1011,
                "humidity": 77,
                "dew_point": 279.04,
                "uvi": 0,
                "clouds": 100,
                "visibility": 10000,
                "wind_speed": 8.75,
                "wind_deg": 211,
                "wind_gust": 19.18,
                "weather": [
                    {
                        "id": 500,
                        "main": "Rain",
                        "description": "light rain",
                        "icon": "10n"
                    }
                ],
                "pop": 1,
                "rain": {
                    "1h": 0.21
                }
            },
            {
                "dt": 1673737200,
                "temp": 284.13,
                "feels_like": 283.19,
                "pressure": 1010,
                "humidity": 73,
                "dew_point": 278.66,
                "uvi": 0,
                "clouds": 100,
                "visibility": 10000,
                "wind_speed": 8.5,
                "wind_deg": 218,
                "wind_gust": 18.51,
                "weather": [
                    {
                        "id": 804,
                        "main": "Clouds",
                        "description": "overcast clouds",
                        "icon": "04n"
                    }
                ],
                "pop": 0.8
            },
            {
                "dt": 1673740800,
                "temp": 283.85,
                "feels_like": 282.93,
                "pressure": 1009,
                "humidity": 75,
                "dew_point": 278.7,
                "uvi": 0,
                "clouds": 100,
                "visibility": 10000,
                "wind_speed": 7.98,
                "wind_deg": 218,
                "wind_gust": 18.53,
                "weather": [
                    {
                        "id": 500,
                        "main": "Rain",
                        "description": "light rain",
                        "icon": "10n"
                    }
                ],
                "pop": 1,
                "rain": {
                    "1h": 0.17
                }
            },
            {
                "dt": 1673744400,
                "temp": 283.59,
                "feels_like": 282.83,
                "pressure": 1009,
                "humidity": 82,
                "dew_point": 279.68,
                "uvi": 0,
                "clouds": 100,
                "visibility": 10000,
                "wind_speed": 8.24,
                "wind_deg": 215,
                "wind_gust": 19.33,
                "weather": [
                    {
                        "id": 500,
                        "main": "Rain",
                        "description": "light rain",
                        "icon": "10n"
                    }
                ],
                "pop": 0.92,
                "rain": {
                    "1h": 0.32
                }
            },
            {
                "dt": 1673748000,
                "temp": 283.47,
                "feels_like": 282.72,
                "pressure": 1008,
                "humidity": 83,
                "dew_point": 279.81,
                "uvi": 0,
                "clouds": 100,
                "visibility": 10000,
                "wind_speed": 8.31,
                "wind_deg": 212,
                "wind_gust": 19.66,
                "weather": [
                    {
                        "id": 500,
                        "main": "Rain",
                        "description": "light rain",
                        "icon": "10n"
                    }
                ],
                "pop": 0.96,
                "rain": {
                    "1h": 0.33
                }
            },
            {
                "dt": 1673751600,
                "temp": 283.2,
                "feels_like": 282.4,
                "pressure": 1007,
                "humidity": 82,
                "dew_point": 279.53,
                "uvi": 0,
                "clouds": 100,
                "visibility": 10000,
                "wind_speed": 8.59,
                "wind_deg": 209,
                "wind_gust": 19.83,
                "weather": [
                    {
                        "id": 500,
                        "main": "Rain",
                        "description": "light rain",
                        "icon": "10n"
                    }
                ],
                "pop": 1,
                "rain": {
                    "1h": 0.59
                }
            },
            {
                "dt": 1673755200,
                "temp": 283.37,
                "feels_like": 282.61,
                "pressure": 1007,
                "humidity": 83,
                "dew_point": 279.65,
                "uvi": 0,
                "clouds": 100,
                "visibility": 10000,
                "wind_speed": 9.1,
                "wind_deg": 213,
                "wind_gust": 20.32,
                "weather": [
                    {
                        "id": 500,
                        "main": "Rain",
                        "description": "light rain",
                        "icon": "10n"
                    }
                ],
                "pop": 1,
                "rain": {
                    "1h": 0.45
                }
            },
            {
                "dt": 1673758800,
                "temp": 283.53,
                "feels_like": 282.71,
                "pressure": 1006,
                "humidity": 80,
                "dew_point": 279.22,
                "uvi": 0,
                "clouds": 100,
                "visibility": 10000,
                "wind_speed": 8.67,
                "wind_deg": 212,
                "wind_gust": 20.45,
                "weather": [
                    {
                        "id": 500,
                        "main": "Rain",
                        "description": "light rain",
                        "icon": "10n"
                    }
                ],
                "pop": 1,
                "rain": {
                    "1h": 0.13
                }
            },
            {
                "dt": 1673762400,
                "temp": 283.82,
                "feels_like": 282.98,
                "pressure": 1006,
                "humidity": 78,
                "dew_point": 279.17,
                "uvi": 0,
                "clouds": 100,
                "visibility": 10000,
                "wind_speed": 9.81,
                "wind_deg": 217,
                "wind_gust": 20.97,
                "weather": [
                    {
                        "id": 500,
                        "main": "Rain",
                        "description": "light rain",
                        "icon": "10n"
                    }
                ],
                "pop": 1,
                "rain": {
                    "1h": 0.15
                }
            },
            {
                "dt": 1673766000,
                "temp": 282.45,
                "feels_like": 279.32,
                "pressure": 1007,
                "humidity": 89,
                "dew_point": 279.87,
                "uvi": 0,
                "clouds": 100,
                "visibility": 7124,
                "wind_speed": 6.57,
                "wind_deg": 266,
                "wind_gust": 15.02,
                "weather": [
                    {
                        "id": 501,
                        "main": "Rain",
                        "description": "moderate rain",
                        "icon": "10n"
                    }
                ],
                "pop": 0.82,
                "rain": {
                    "1h": 1.12
                }
            },
            {
                "dt": 1673769600,
                "temp": 277.87,
                "feels_like": 275.72,
                "pressure": 1010,
                "humidity": 96,
                "dew_point": 276.35,
                "uvi": 0.03,
                "clouds": 100,
                "visibility": 1917,
                "wind_speed": 2.5,
                "wind_deg": 351,
                "wind_gust": 5.5,
                "weather": [
                    {
                        "id": 501,
                        "main": "Rain",
                        "description": "moderate rain",
                        "icon": "10d"
                    }
                ],
                "pop": 0.94,
                "rain": {
                    "1h": 2.45
                }
            },
            {
                "dt": 1673773200,
                "temp": 278.06,
                "feels_like": 278.06,
                "pressure": 1012,
                "humidity": 93,
                "dew_point": 276.19,
                "uvi": 0.08,
                "clouds": 100,
                "visibility": 1922,
                "wind_speed": 1.14,
                "wind_deg": 274,
                "wind_gust": 3.4,
                "weather": [
                    {
                        "id": 501,
                        "main": "Rain",
                        "description": "moderate rain",
                        "icon": "10d"
                    }
                ],
                "pop": 0.98,
                "rain": {
                    "1h": 1.39
                }
            },
            {
                "dt": 1673776800,
                "temp": 278.12,
                "feels_like": 275.59,
                "pressure": 1012,
                "humidity": 94,
                "dew_point": 276.32,
                "uvi": 0.15,
                "clouds": 100,
                "visibility": 1692,
                "wind_speed": 3.04,
                "wind_deg": 231,
                "wind_gust": 6.19,
                "weather": [
                    {
                        "id": 501,
                        "main": "Rain",
                        "description": "moderate rain",
                        "icon": "10d"
                    }
                ],
                "pop": 0.98,
                "rain": {
                    "1h": 1.24
                }
            },
            {
                "dt": 1673780400,
                "temp": 277.51,
                "feels_like": 273.68,
                "pressure": 1012,
                "humidity": 96,
                "dew_point": 275.97,
                "uvi": 0.2,
                "clouds": 100,
                "visibility": 2976,
                "wind_speed": 5.01,
                "wind_deg": 225,
                "wind_gust": 8.81,
                "weather": [
                    {
                        "id": 500,
                        "main": "Rain",
                        "description": "light rain",
                        "icon": "10d"
                    }
                ],
                "pop": 1,
                "rain": {
                    "1h": 0.75
                }
            },
            {
                "dt": 1673784000,
                "temp": 276.83,
                "feels_like": 272.65,
                "pressure": 1013,
                "humidity": 96,
                "dew_point": 275.44,
                "uvi": 0.2,
                "clouds": 100,
                "visibility": 1913,
                "wind_speed": 5.39,
                "wind_deg": 232,
                "wind_gust": 10.29,
                "weather": [
                    {
                        "id": 500,
                        "main": "Rain",
                        "description": "light rain",
                        "icon": "10d"
                    }
                ],
                "pop": 1,
                "rain": {
                    "1h": 0.62
                }
            },
            {
                "dt": 1673787600,
                "temp": 276.76,
                "feels_like": 273.35,
                "pressure": 1014,
                "humidity": 96,
                "dew_point": 275.32,
                "uvi": 0.42,
                "clouds": 100,
                "visibility": 2915,
                "wind_speed": 3.92,
                "wind_deg": 242,
                "wind_gust": 7.87,
                "weather": [
                    {
                        "id": 500,
                        "main": "Rain",
                        "description": "light rain",
                        "icon": "10d"
                    }
                ],
                "pop": 0.9,
                "rain": {
                    "1h": 0.29
                }
            },
            {
                "dt": 1673791200,
                "temp": 277.07,
                "feels_like": 273.56,
                "pressure": 1015,
                "humidity": 94,
                "dew_point": 275.28,
                "uvi": 0.24,
                "clouds": 100,
                "visibility": 3121,
                "wind_speed": 4.21,
                "wind_deg": 223,
                "wind_gust": 8.01,
                "weather": [
                    {
                        "id": 500,
                        "main": "Rain",
                        "description": "light rain",
                        "icon": "10d"
                    }
                ],
                "pop": 0.9,
                "rain": {
                    "1h": 0.57
                }
            },
            {
                "dt": 1673794800,
                "temp": 277.44,
                "feels_like": 273.39,
                "pressure": 1015,
                "humidity": 86,
                "dew_point": 274.31,
                "uvi": 0.08,
                "clouds": 95,
                "visibility": 10000,
                "wind_speed": 5.45,
                "wind_deg": 223,
                "wind_gust": 9.97,
                "weather": [
                    {
                        "id": 500,
                        "main": "Rain",
                        "description": "light rain",
                        "icon": "10d"
                    }
                ],
                "pop": 0.83,
                "rain": {
                    "1h": 0.15
                }
            },
            {
                "dt": 1673798400,
                "temp": 276.94,
                "feels_like": 272.8,
                "pressure": 1015,
                "humidity": 85,
                "dew_point": 273.74,
                "uvi": 0,
                "clouds": 86,
                "visibility": 10000,
                "wind_speed": 5.35,
                "wind_deg": 218,
                "wind_gust": 11.1,
                "weather": [
                    {
                        "id": 804,
                        "main": "Clouds",
                        "description": "overcast clouds",
                        "icon": "04d"
                    }
                ],
                "pop": 0.69
            },
            {
                "dt": 1673802000,
                "temp": 276.87,
                "feels_like": 272.6,
                "pressure": 1015,
                "humidity": 84,
                "dew_point": 273.52,
                "uvi": 0,
                "clouds": 78,
                "visibility": 10000,
                "wind_speed": 5.59,
                "wind_deg": 218,
                "wind_gust": 11.87,
                "weather": [
                    {
                        "id": 803,
                        "main": "Clouds",
                        "description": "broken clouds",
                        "icon": "04n"
                    }
                ],
                "pop": 0.63
            },
            {
                "dt": 1673805600,
                "temp": 276.74,
                "feels_like": 272.53,
                "pressure": 1015,
                "humidity": 84,
                "dew_point": 273.4,
                "uvi": 0,
                "clouds": 74,
                "visibility": 10000,
                "wind_speed": 5.39,
                "wind_deg": 216,
                "wind_gust": 12.18,
                "weather": [
                    {
                        "id": 803,
                        "main": "Clouds",
                        "description": "broken clouds",
                        "icon": "04n"
                    }
                ],
                "pop": 0.56
            },
            {
                "dt": 1673809200,
                "temp": 276.26,
                "feels_like": 272.14,
                "pressure": 1015,
                "humidity": 83,
                "dew_point": 272.69,
                "uvi": 0,
                "clouds": 43,
                "visibility": 10000,
                "wind_speed": 4.96,
                "wind_deg": 213,
                "wind_gust": 12.54,
                "weather": [
                    {
                        "id": 802,
                        "main": "Clouds",
                        "description": "scattered clouds",
                        "icon": "03n"
                    }
                ],
                "pop": 0
            },
            {
                "dt": 1673812800,
                "temp": 275.89,
                "feels_like": 271.85,
                "pressure": 1015,
                "humidity": 81,
                "dew_point": 271.94,
                "uvi": 0,
                "clouds": 41,
                "visibility": 10000,
                "wind_speed": 4.64,
                "wind_deg": 212,
                "wind_gust": 12.29,
                "weather": [
                    {
                        "id": 802,
                        "main": "Clouds",
                        "description": "scattered clouds",
                        "icon": "03n"
                    }
                ],
                "pop": 0
            },
            {
                "dt": 1673816400,
                "temp": 275.71,
                "feels_like": 271.57,
                "pressure": 1014,
                "humidity": 81,
                "dew_point": 271.84,
                "uvi": 0,
                "clouds": 45,
                "visibility": 10000,
                "wind_speed": 4.74,
                "wind_deg": 213,
                "wind_gust": 12.22,
                "weather": [
                    {
                        "id": 802,
                        "main": "Clouds",
                        "description": "scattered clouds",
                        "icon": "03n"
                    }
                ],
                "pop": 0
            },
            {
                "dt": 1673820000,
                "temp": 275.86,
                "feels_like": 271.88,
                "pressure": 1013,
                "humidity": 81,
                "dew_point": 272.18,
                "uvi": 0,
                "clouds": 58,
                "visibility": 10000,
                "wind_speed": 4.52,
                "wind_deg": 211,
                "wind_gust": 11.25,
                "weather": [
                    {
                        "id": 803,
                        "main": "Clouds",
                        "description": "broken clouds",
                        "icon": "04n"
                    }
                ],
                "pop": 0
            },
            {
                "dt": 1673823600,
                "temp": 275.72,
                "feels_like": 271.82,
                "pressure": 1012,
                "humidity": 83,
                "dew_point": 272.25,
                "uvi": 0,
                "clouds": 63,
                "visibility": 10000,
                "wind_speed": 4.33,
                "wind_deg": 208,
                "wind_gust": 11.19,
                "weather": [
                    {
                        "id": 803,
                        "main": "Clouds",
                        "description": "broken clouds",
                        "icon": "04n"
                    }
                ],
                "pop": 0
            },
            {
                "dt": 1673827200,
                "temp": 275.62,
                "feels_like": 271.76,
                "pressure": 1011,
                "humidity": 83,
                "dew_point": 272.06,
                "uvi": 0,
                "clouds": 67,
                "visibility": 10000,
                "wind_speed": 4.22,
                "wind_deg": 204,
                "wind_gust": 11.12,
                "weather": [
                    {
                        "id": 803,
                        "main": "Clouds",
                        "description": "broken clouds",
                        "icon": "04n"
                    }
                ],
                "pop": 0
            },
            {
                "dt": 1673830800,
                "temp": 275.59,
                "feels_like": 271.87,
                "pressure": 1009,
                "humidity": 82,
                "dew_point": 272.01,
                "uvi": 0,
                "clouds": 63,
                "visibility": 10000,
                "wind_speed": 3.99,
                "wind_deg": 200,
                "wind_gust": 11.02,
                "weather": [
                    {
                        "id": 803,
                        "main": "Clouds",
                        "description": "broken clouds",
                        "icon": "04n"
                    }
                ],
                "pop": 0
            },
            {
                "dt": 1673834400,
                "temp": 275.61,
                "feels_like": 272.3,
                "pressure": 1008,
                "humidity": 82,
                "dew_point": 272,
                "uvi": 0,
                "clouds": 66,
                "visibility": 10000,
                "wind_speed": 3.4,
                "wind_deg": 195,
                "wind_gust": 10.27,
                "weather": [
                    {
                        "id": 803,
                        "main": "Clouds",
                        "description": "broken clouds",
                        "icon": "04n"
                    }
                ],
                "pop": 0
            },
            {
                "dt": 1673838000,
                "temp": 275.06,
                "feels_like": 272.05,
                "pressure": 1006,
                "humidity": 83,
                "dew_point": 271.58,
                "uvi": 0,
                "clouds": 58,
                "visibility": 10000,
                "wind_speed": 2.88,
                "wind_deg": 182,
                "wind_gust": 7.46,
                "weather": [
                    {
                        "id": 803,
                        "main": "Clouds",
                        "description": "broken clouds",
                        "icon": "04n"
                    }
                ],
                "pop": 0
            },
            {
                "dt": 1673841600,
                "temp": 274.35,
                "feels_like": 271.04,
                "pressure": 1004,
                "humidity": 84,
                "dew_point": 271.03,
                "uvi": 0,
                "clouds": 47,
                "visibility": 10000,
                "wind_speed": 3.06,
                "wind_deg": 160,
                "wind_gust": 5.61,
                "weather": [
                    {
                        "id": 802,
                        "main": "Clouds",
                        "description": "scattered clouds",
                        "icon": "03n"
                    }
                ],
                "pop": 0
            },
            {
                "dt": 1673845200,
                "temp": 274.32,
                "feels_like": 270.59,
                "pressure": 1001,
                "humidity": 83,
                "dew_point": 270.76,
                "uvi": 0,
                "clouds": 47,
                "visibility": 10000,
                "wind_speed": 3.59,
                "wind_deg": 149,
                "wind_gust": 6.85,
                "weather": [
                    {
                        "id": 802,
                        "main": "Clouds",
                        "description": "scattered clouds",
                        "icon": "03n"
                    }
                ],
                "pop": 0
            },
            {
                "dt": 1673848800,
                "temp": 274.94,
                "feels_like": 270.95,
                "pressure": 999,
                "humidity": 82,
                "dew_point": 271.19,
                "uvi": 0,
                "clouds": 56,
                "visibility": 10000,
                "wind_speed": 4.18,
                "wind_deg": 154,
                "wind_gust": 9.09,
                "weather": [
                    {
                        "id": 803,
                        "main": "Clouds",
                        "description": "broken clouds",
                        "icon": "04n"
                    }
                ],
                "pop": 0
            },
            {
                "dt": 1673852400,
                "temp": 275.6,
                "feels_like": 271.78,
                "pressure": 997,
                "humidity": 75,
                "dew_point": 270.69,
                "uvi": 0,
                "clouds": 100,
                "visibility": 10000,
                "wind_speed": 4.16,
                "wind_deg": 166,
                "wind_gust": 10.13,
                "weather": [
                    {
                        "id": 804,
                        "main": "Clouds",
                        "description": "overcast clouds",
                        "icon": "04n"
                    }
                ],
                "pop": 0
            },
            {
                "dt": 1673856000,
                "temp": 276.45,
                "feels_like": 272.36,
                "pressure": 997,
                "humidity": 68,
                "dew_point": 270.14,
                "uvi": 0.08,
                "clouds": 100,
                "visibility": 10000,
                "wind_speed": 5,
                "wind_deg": 183,
                "wind_gust": 15.84,
                "weather": [
                    {
                        "id": 804,
                        "main": "Clouds",
                        "description": "overcast clouds",
                        "icon": "04d"
                    }
                ],
                "pop": 0.07
            },
            {
                "dt": 1673859600,
                "temp": 276.5,
                "feels_like": 271.73,
                "pressure": 996,
                "humidity": 80,
                "dew_point": 272.39,
                "uvi": 0.23,
                "clouds": 100,
                "visibility": 10000,
                "wind_speed": 6.52,
                "wind_deg": 185,
                "wind_gust": 18.14,
                "weather": [
                    {
                        "id": 500,
                        "main": "Rain",
                        "description": "light rain",
                        "icon": "10d"
                    }
                ],
                "pop": 0.44,
                "rain": {
                    "1h": 0.72
                }
            },
            {
                "dt": 1673863200,
                "temp": 277.98,
                "feels_like": 273.04,
                "pressure": 995,
                "humidity": 80,
                "dew_point": 273.99,
                "uvi": 0.2,
                "clouds": 100,
                "visibility": 10000,
                "wind_speed": 8.18,
                "wind_deg": 205,
                "wind_gust": 19.44,
                "weather": [
                    {
                        "id": 500,
                        "main": "Rain",
                        "description": "light rain",
                        "icon": "10d"
                    }
                ],
                "pop": 0.59,
                "rain": {
                    "1h": 0.67
                }
            },
            {
                "dt": 1673866800,
                "temp": 277.88,
                "feels_like": 272.7,
                "pressure": 995,
                "humidity": 85,
                "dew_point": 274.53,
                "uvi": 0.25,
                "clouds": 100,
                "visibility": 9259,
                "wind_speed": 8.89,
                "wind_deg": 224,
                "wind_gust": 17.52,
                "weather": [
                    {
                        "id": 500,
                        "main": "Rain",
                        "description": "light rain",
                        "icon": "10d"
                    }
                ],
                "pop": 0.82,
                "rain": {
                    "1h": 0.76
                }
            }
        ]
    }
}